elevation/__init__.py
elevation/cli.py
elevation/datasource.mk
elevation/datasource.py
elevation/spatial.py
elevation/util.py
elevation/version.py
elevation-1.1.3.dist-info/LICENSE
elevation-1.1.3.dist-info/METADATA
elevation-1.1.3.dist-info/WHEEL
elevation-1.1.3.dist-info/entry_points.txt
elevation-1.1.3.dist-info/top_level.txt
elevation-1.1.3.dist-info/zip-safe
elevation-1.1.3.dist-info/RECORD
