Metadata-Version: 2.1
Name: elevation
Version: 1.1.3
Summary: Python script to download global terrain digital elevation models, SRTM 30m DEM and SRTM 90m DEM.
Home-page: http://elevation.bopen.eu
Author: B-Open Solutions srl, Alessandro Amici
Author-email: info@bopen.eu
License: Apache License Version 2.0
Keywords: script download SRTM DEM DTM global digital elevation terrain model
Platform: UNKNOWN
Classifier: Development Status :: 5 - Production/Stable
Classifier: Intended Audience :: Developers
Classifier: Intended Audience :: Science/Research
Classifier: Programming Language :: Python
Classifier: Programming Language :: Python :: 3
Classifier: Programming Language :: Python :: 3.6
Classifier: Programming Language :: Python :: 3.7
Classifier: Programming Language :: Python :: 3.8
Classifier: Programming Language :: Python :: 3.9
Classifier: Programming Language :: Python :: Implementation :: CPython
Classifier: Operating System :: OS Independent
Classifier: License :: OSI Approved :: Apache Software License
Classifier: Topic :: Scientific/Engineering :: GIS
Provides-Extra: reference
